dc43_service_backends/__init__.py
dc43_service_backends/auth.py
dc43_service_backends/bootstrap.py
dc43_service_backends/config.py
dc43_service_backends/server.py
dc43_service_backends/web.py
dc43_service_backends/webapp.py
dc43_service_backends/config/default.toml
dc43_service_backends/contracts/__init__.py
dc43_service_backends/contracts/drafting.py
dc43_service_backends/contracts/backend/__init__.py
dc43_service_backends/contracts/backend/drafting.py
dc43_service_backends/contracts/backend/interface.py
dc43_service_backends/contracts/backend/local.py
dc43_service_backends/contracts/backend/stores/__init__.py
dc43_service_backends/contracts/backend/stores/_sql_common.py
dc43_service_backends/contracts/backend/stores/collibra.py
dc43_service_backends/contracts/backend/stores/delta.py
dc43_service_backends/contracts/backend/stores/filesystem.py
dc43_service_backends/contracts/backend/stores/interface.py
dc43_service_backends/contracts/backend/stores/sql.py
dc43_service_backends/core/__init__.py
dc43_service_backends/core/odcs.py
dc43_service_backends/core/odps.py
dc43_service_backends/core/versioning.py
dc43_service_backends/data_products/__init__.py
dc43_service_backends/data_products/backend/__init__.py
dc43_service_backends/data_products/backend/_shared.py
dc43_service_backends/data_products/backend/collibra.py
dc43_service_backends/data_products/backend/delta.py
dc43_service_backends/data_products/backend/interface.py
dc43_service_backends/data_products/backend/local.py
dc43_service_backends/data_products/backend/stores/__init__.py
dc43_service_backends/data_products/backend/stores/delta.py
dc43_service_backends/data_products/backend/stores/filesystem.py
dc43_service_backends/data_products/backend/stores/interface.py
dc43_service_backends/data_products/backend/stores/memory.py
dc43_service_backends/data_products/backend/stores/sql.py
dc43_service_backends/data_quality/__init__.py
dc43_service_backends/data_quality/backend/__init__.py
dc43_service_backends-0.32.0.0.dist-info/METADATA
dc43_service_backends-0.32.0.0.dist-info/WHEEL
dc43_service_backends-0.32.0.0.dist-info/top_level.txt
dc43_service_backends-0.32.0.0.dist-info/RECORD
