Metadata-Version: 2.4
Name: dc43-service-backends
Version: 0.32.0.0
Summary: Backend service implementations for dc43
Author: Andy Petrella
Classifier: Programming Language :: Python :: 3
Classifier: License :: OSI Approved :: MIT License
Classifier: Operating System :: OS Independent
Requires-Python: >=3.11
Requires-Dist: dc43-core>=0.32.0.0
Requires-Dist: dc43-service-clients>=0.0.3
Requires-Dist: open-data-contract-standard==3.0.2
Requires-Dist: sqlalchemy>=2.0
Requires-Dist: tomlkit>=0.12
Provides-Extra: spark
Requires-Dist: pyspark>=3.4; extra == "spark"
Provides-Extra: http
Requires-Dist: fastapi>=0.118.0; extra == "http"
Provides-Extra: sql
Requires-Dist: sqlalchemy>=2.0; extra == "sql"
Provides-Extra: test
Requires-Dist: fastapi>=0.118.0; extra == "test"
Requires-Dist: httpx>=0.24; extra == "test"
Requires-Dist: pyspark>=3.4; extra == "test"
Requires-Dist: dc43-service-clients[lineage,test]>=0.32.0.0; extra == "test"
